README.rst
setup.py
sfs_upload/__init__.py
sfs_upload/sfs_upload.py
sfs_upload.egg-info/PKG-INFO
sfs_upload.egg-info/SOURCES.txt
sfs_upload.egg-info/dependency_links.txt
sfs_upload.egg-info/requires.txt
sfs_upload.egg-info/top_level.txt