Metadata-Version: 1.0
Name: sfs-upload
Version: 0.1
Summary: Upload files to SFS: https://github.com/the-louie/simple-file-sharer
Home-page: https://github.com/spillevink/sfs_upload
Author: Jakob Hedman
Author-email: jakob@hedman.email
License: GNU GPLv3
Platform: UNKNOWN
